{
  "version": 4,
  "latest_version": "v1.2.2",
  "min_supported_version": "v1.2.1",
  "release_date": "2026-04-07",
  "download_url": "https://github.com/Abnerla/AI_paper/releases",
  "changelog": [
    {
      "version": "v1.2.2",
      "date": "2026-04-07",
      "changes": [
      "修复 重置后输入接到灰色提示文后面的错误",
      "修复 模型列表里当前模型的状态文案、启用按钮显示和删除入口",
      "修复 模型列表弹窗首击无效的问题",
      "修复 模式切换菜单内容被遮挡的问题",
      "修复 深色模式切换浅色模式按钮变黑的问题",

      "优化 模型列表删除模型的逻辑",
      "优化 论文大纲的内容不能用滚轮上下滑动",

      "增加论文大纲右键删除的功能"
      ]
    }
  ],
  "update_message": ""
}
